fastapi_jet/__init__.py
fastapi_jet/__main__.py
fastapi_jet/cli.py
fastapi_jet/commands/__init__.py
fastapi_jet/commands/applist.py
fastapi_jet/commands/runserver.py
fastapi_jet/commands/startapp.py
fastapi_jet/commands/startproject.py
fastapi_jet/constants.py
fastapi_jet/context.py
fastapi_jet/decorators.py
fastapi_jet/generator.py
fastapi_jet/templates/__init__.py
fastapi_jet/templates/app/__init__.py
fastapi_jet/templates/app/cookiecutter.json
fastapi_jet/templates/app/{{cookiecutter.folder_name}}/__init__.py
fastapi_jet/templates/app/{{cookiecutter.folder_name}}/config.py
fastapi_jet/templates/app/{{cookiecutter.folder_name}}/constants.py
fastapi_jet/templates/app/{{cookiecutter.folder_name}}/exceptions.py
fastapi_jet/templates/app/{{cookiecutter.folder_name}}/models.py
fastapi_jet/templates/app/{{cookiecutter.folder_name}}/routers.py
fastapi_jet/templates/app/{{cookiecutter.folder_name}}/schemas.py
fastapi_jet/templates/app/{{cookiecutter.folder_name}}/service.py
fastapi_jet/templates/app/{{cookiecutter.folder_name}}/utils.py
fastapi_jet/templates/project/__init__.py
fastapi_jet/templates/project/cookiecutter.json
fastapi_jet/templates/project/{{cookiecutter.folder_name}}/.env
fastapi_jet/templates/project/{{cookiecutter.folder_name}}/README.md
fastapi_jet/templates/project/{{cookiecutter.folder_name}}/apps/__init__.py
fastapi_jet/templates/project/{{cookiecutter.folder_name}}/base/__init__.py
fastapi_jet/templates/project/{{cookiecutter.folder_name}}/base/core.py
fastapi_jet/templates/project/{{cookiecutter.folder_name}}/base/main.py
fastapi_jet/templates/project/{{cookiecutter.folder_name}}/middlewares/__init__.py
fastapi_jet/templates/project/{{cookiecutter.folder_name}}/requirements.txt
fastapi_jet/tools.py
fastapi_jet/utils.py
fastapi_jet-1.1.5.dist-info/LICENSE
fastapi_jet-1.1.5.dist-info/METADATA
fastapi_jet-1.1.5.dist-info/WHEEL
fastapi_jet-1.1.5.dist-info/entry_points.txt
fastapi_jet-1.1.5.dist-info/RECORD
