Metadata-Version: 2.1
Name: fastapi-jet
Version: 1.1.5
Summary: Managing FastAPI projects made easy.
Home-page: https://github.com/its0x4d/fastapi-jet
License: MIT
Author: Mostafa Mosavi
Author-email: mostafa.uwsgi@gmail.com
Requires-Python: >=3.8,<4.0
Classifier: License :: OSI Approved :: MIT License
Classifier: Programming Language :: Python :: 3
Classifier: Programming Language :: Python :: 3.8
Classifier: Programming Language :: Python :: 3.9
Classifier: Programming Language :: Python :: 3.10
Classifier: Programming Language :: Python :: 3.11
Classifier: Programming Language :: Python :: 3.12
Requires-Dist: cookiecutter (>=2.5.0,<3.0.0)
Requires-Dist: fastapi (>=0.105.0,<0.106.0)
Requires-Dist: pydantic (>=2.5.2,<3.0.0)
Requires-Dist: python-dotenv (>=1.0.0,<2.0.0)
Requires-Dist: questionary (>=2.0.1,<3.0.0)
Requires-Dist: tabulate (>=0.9.0,<0.10.0)
Requires-Dist: typer (>=0.9.0,<0.10.0)
Requires-Dist: uvicorn (>=0.24.0.post1,<0.25.0)
Project-URL: Repository, https://github.com/its0x4d/fastapi-jet
